advance_touch.py
advance_touch-1.0.2.dist-info/DESCRIPTION.rst
advance_touch-1.0.2.dist-info/METADATA
advance_touch-1.0.2.dist-info/RECORD
advance_touch-1.0.2.dist-info/WHEEL
advance_touch-1.0.2.dist-info/entry_points.txt
advance_touch-1.0.2.dist-info/metadata.json
advance_touch-1.0.2.dist-info/top_level.txt
